common/__init__.py
common/base.py
common/cache.py
common/circuit_breaker.py
common/config.py
common/exceptions.py
common/health.py
common/logging.py
common/metrics.py
common/py.typed
common/rate_limiter.py
common/retry.py
common/rule_validation.py
common/serializers.py
common/testing.py
common/engines/__init__.py
common/engines/aggregation.py
common/engines/base.py
common/engines/batch.py
common/engines/chain.py
common/engines/config.py
common/engines/context.py
common/engines/great_expectations.py
common/engines/lifecycle.py
common/engines/metrics.py
common/engines/pandera.py
common/engines/plugin.py
common/engines/registry.py
common/engines/truthound.py
common/engines/version.py
common/exporters/__init__.py
common/exporters/prometheus.py
common/opentelemetry/__init__.py
common/opentelemetry/config.py
common/opentelemetry/exceptions.py
common/opentelemetry/testing.py
common/opentelemetry/types.py
common/opentelemetry/bridge/__init__.py
common/opentelemetry/bridge/context.py
common/opentelemetry/bridge/metrics.py
common/opentelemetry/bridge/tracing.py
common/opentelemetry/exporters/__init__.py
common/opentelemetry/integration/__init__.py
common/opentelemetry/integration/engine_hook.py
common/opentelemetry/integration/sampling.py
common/opentelemetry/providers/__init__.py
common/opentelemetry/providers/meter.py
common/opentelemetry/providers/resource.py
common/opentelemetry/providers/tracer.py
common/opentelemetry/semantic/__init__.py
common/opentelemetry/semantic/attributes.py
packages/airflow/README.md
packages/airflow/pyproject.toml
packages/airflow/src/truthound_airflow/__init__.py
packages/airflow/src/truthound_airflow/version.py
packages/airflow/src/truthound_airflow/hooks/__init__.py
packages/airflow/src/truthound_airflow/hooks/base.py
packages/airflow/src/truthound_airflow/operators/__init__.py
packages/airflow/src/truthound_airflow/operators/anomaly.py
packages/airflow/src/truthound_airflow/operators/base.py
truthound_orchestration-1.1.0.dist-info/METADATA
truthound_orchestration-1.1.0.dist-info/WHEEL
truthound_orchestration-1.1.0.dist-info/entry_points.txt
truthound_orchestration-1.1.0.dist-info/licenses/LICENSE
truthound_orchestration-1.1.0.dist-info/RECORD
