Metadata-Version: 2.4
Name: truthound-orchestration
Version: 1.1.0
Summary: Official orchestration integrations for Truthound data quality framework
Project-URL: Homepage, https://github.com/seadonggyun4/truthound-orchestration
Project-URL: Documentation, https://truthound.netlify.app/
Project-URL: Repository, https://github.com/seadonggyun4/truthound-orchestration
Project-URL: Issues, https://github.com/seadonggyun4/truthound-orchestration/issues
Author-email: Truthound Team <team@truthound.dev>
License: Apache-2.0
License-File: LICENSE
Keywords: airflow,dagster,data-quality,dbt,kestra,mage,prefect,truthound,validation
Classifier: Development Status :: 3 - Alpha
Classifier: Intended Audience :: Developers
Classifier: License :: OSI Approved :: Apache Software License
Classifier: Operating System :: OS Independent
Classifier: Programming Language :: Python :: 3
Classifier: Programming Language :: Python :: 3.11
Classifier: Programming Language :: Python :: 3.12
Classifier: Programming Language :: Python :: 3.13
Classifier: Topic :: Software Development :: Libraries :: Python Modules
Classifier: Topic :: Software Development :: Quality Assurance
Classifier: Typing :: Typed
Requires-Python: >=3.11
Requires-Dist: polars>=0.20.0
Provides-Extra: airflow
Requires-Dist: apache-airflow>=2.6.0; extra == 'airflow'
Provides-Extra: all
Requires-Dist: apache-airflow>=2.6.0; extra == 'all'
Requires-Dist: dagster>=1.5.0; extra == 'all'
Requires-Dist: kestra>=0.15.0; extra == 'all'
Requires-Dist: mage-ai>=0.9.0; extra == 'all'
Requires-Dist: mypy>=1.13.0; extra == 'all'
Requires-Dist: opentelemetry-api>=1.20.0; extra == 'all'
Requires-Dist: opentelemetry-exporter-otlp-proto-grpc>=1.20.0; extra == 'all'
Requires-Dist: opentelemetry-exporter-otlp-proto-http>=1.20.0; extra == 'all'
Requires-Dist: opentelemetry-sdk>=1.20.0; extra == 'all'
Requires-Dist: pre-commit>=3.6.0; extra == 'all'
Requires-Dist: prefect>=2.14.0; extra == 'all'
Requires-Dist: pytest-asyncio>=0.24.0; extra == 'all'
Requires-Dist: pytest-cov>=4.1.0; extra == 'all'
Requires-Dist: pytest-xdist>=3.5.0; extra == 'all'
Requires-Dist: pytest>=8.0.0; extra == 'all'
Requires-Dist: pyyaml>=6.0.0; extra == 'all'
Requires-Dist: ruff>=0.8.0; extra == 'all'
Provides-Extra: dagster
Requires-Dist: dagster>=1.5.0; extra == 'dagster'
Provides-Extra: dev
Requires-Dist: mypy>=1.13.0; extra == 'dev'
Requires-Dist: pre-commit>=3.6.0; extra == 'dev'
Requires-Dist: pytest-asyncio>=0.24.0; extra == 'dev'
Requires-Dist: pytest-cov>=4.1.0; extra == 'dev'
Requires-Dist: pytest-xdist>=3.5.0; extra == 'dev'
Requires-Dist: pytest>=8.0.0; extra == 'dev'
Requires-Dist: pyyaml>=6.0.0; extra == 'dev'
Requires-Dist: ruff>=0.8.0; extra == 'dev'
Provides-Extra: kestra
Requires-Dist: kestra>=0.15.0; extra == 'kestra'
Requires-Dist: pyyaml>=6.0.0; extra == 'kestra'
Provides-Extra: mage
Requires-Dist: mage-ai>=0.9.0; extra == 'mage'
Provides-Extra: opentelemetry
Requires-Dist: opentelemetry-api>=1.20.0; extra == 'opentelemetry'
Requires-Dist: opentelemetry-exporter-otlp-proto-grpc>=1.20.0; extra == 'opentelemetry'
Requires-Dist: opentelemetry-exporter-otlp-proto-http>=1.20.0; extra == 'opentelemetry'
Requires-Dist: opentelemetry-sdk>=1.20.0; extra == 'opentelemetry'
Provides-Extra: prefect
Requires-Dist: prefect>=2.14.0; extra == 'prefect'
